llama/.env
llama/__init__.py
llama/settings.py
llama/starter.py
little_llama-0.0.2.dist-info/METADATA
little_llama-0.0.2.dist-info/WHEEL
little_llama-0.0.2.dist-info/entry_points.txt
little_llama-0.0.2.dist-info/top_level.txt
little_llama-0.0.2.dist-info/RECORD
