Metadata-Version: 2.1
Name: little_llama
Version: 0.0.2
Summary: Get information from custom text
Home-page: https://git.parstechai.com/parstech-nlp/nlg/parschat-logic/-/tree/feat/sensomatt_doc?ref_type=heads
Author: javad nematollahi
Author-email: javadnematollahi92@gmail.com
Classifier: Programming Language :: Python :: 3
Classifier: License :: OSI Approved :: MIT License
Classifier: Operating System :: OS Independent
Requires-Dist: ai-utils
Requires-Dist: llama-index
Requires-Dist: pydantic
Requires-Dist: pydantic-settings
Requires-Dist: setuptools
